fmts/__about__.py
fmts/__init__.py
fmts/__main__.py
fmts/py.typed
fmts-0.4.1.dist-info/WHEEL
fmts-0.4.1.dist-info/METADATA
fmts-0.4.1.dist-info/RECORD
