Metadata-Version: 2.3
Name: fmts
Version: 0.4.1
Summary: str transformation utils
Keywords: dgpy,str,typed,utils,vanilla
Author: jesse
Author-email: jesse <jessekrubin@gmail.com>
Classifier: Development Status :: 5 - Production/Stable
Classifier: Intended Audience :: Developers
Classifier: License :: OSI Approved :: MIT License
Classifier: Programming Language :: Python
Classifier: Programming Language :: Python :: 3 :: Only
Classifier: Programming Language :: Python :: 3.11
Classifier: Programming Language :: Python :: 3.12
Classifier: Programming Language :: Python :: 3.13
Classifier: Programming Language :: Python :: 3.14
Classifier: Typing :: Typed
Requires-Python: >=3.11, <4.0
Project-URL: Homepage, https://github.com/dynamic-graphics-inc/dgpy-libs/tree/main/libs/fmts
Project-URL: Repository, https://github.com/dynamic-graphics-inc/dgpy-libs
